{
    "entityType": {
        "title": "dataset-ENTITY TYPE",
        "key": "entityType",
        "aggs": "entityType"
    },
    "socio_eco": {
        "title": "dataset-Socio Eco",
        "key": "socio_eco",
        "aggs": "attributes-Mlstr_area__Sociodemographic_economic_characteristics-und"
    },
    "lifestyle": {
        "title": "dataset-Lifestyle",
        "key": "lifestyle",
        "aggs": "attributes-Mlstr_area__Lifestyle_behaviours-und"
    },
    "health_status": {
        "title": "dataset-Health Status",
        "key": "health_status",
        "aggs": "attributes-Mlstr_area__Health_status_functional_limitations-und"
    },
    "diseases": {
        "title": "dataset-Diseases",
        "key": "diseases",
        "aggs": "attributes-Mlstr_area__Diseases-und"
    },
    "symptoms": {
        "title": "dataset-Symptoms",
        "key": "symptoms",
        "aggs": "attributes-Mlstr_area__Symptoms_signs-und"
    },
    "medication": {
        "title": "dataset-Medication",
        "key": "medication",
        "aggs": "attributes-Mlstr_area__Medication_supplements-und"
    },
    "non_pharma": {
        "title": "dataset-Non Pharma",
        "key": "non_pharma",
        "aggs": "attributes-Mlstr_area__Non_pharmacological_interventions-und"
    },
    "health_community": {
        "title": "dataset-Health Community Care",
        "key": "health_community",
        "aggs": "attributes-Mlstr_area__Health_community_care_utilization-und"
    },
    "reproduction": {
        "title": "dataset-Reproduction",
        "key": "reproduction",
        "aggs": "attributes-Mlstr_area__Reproduction-und"
    },
    "harmo_status": {
        "title": "dataset-HARMO STATUS",
        "key": "harmo_status",
        "aggs": "attributes-Mlstr_harmo__status-und"
    },
    "variableType": {
        "title": "dataset-VARIABLE TYPE",
        "key": "variableType",
        "aggs": "variableType"
    },
    "repeatable": {
        "title": "dataset-REPEATABLE",
        "key": "repeatable",
        "aggs": "repeatable"
    },
    "valueType": {
        "title": "dataset-VALUE TYPE",
        "key": "valueType",
        "aggs": "valueType"
    },
    "occurrenceGroup": {
        "title": "dataset-OCCURRENCE GROUP",
        "key": "occurrenceGroup",
        "aggs": "occurrenceGroup"
    },
    "studyIds": {
        "title": "Study-Studies",
        "key": "studyIds",
        "aggs": "studyIds"
    },
    "datasetId": {
        "title": "dataset-DATASETS",
        "key": "datasetId",
        "aggs": "datasetId"
    }
}